opera/__init__.py
opera/opera_mcp.py
opera/pattern_detection.py
opera_mcp-0.1.1.dist-info/licenses/LICENSE
opera_mcp-0.1.1.dist-info/METADATA
opera_mcp-0.1.1.dist-info/WHEEL
opera_mcp-0.1.1.dist-info/entry_points.txt
opera_mcp-0.1.1.dist-info/top_level.txt
opera_mcp-0.1.1.dist-info/RECORD
