Metadata-Version: 2.4
Name: opera-mcp
Version: 0.1.1
Summary: OPERA - Operadic pattern discovery and verification system
Author: Isaac
License: GNOSYS Personal Builder License (GPBL) v1.0
Keywords: mcp ai patterns opera operadic starsystem
Classifier: Development Status :: 3 - Alpha
Classifier: Intended Audience :: Developers
Classifier: Programming Language :: Python :: 3
Classifier: Programming Language :: Python :: 3.10
Classifier: Programming Language :: Python :: 3.11
Requires-Python: >=3.10
License-File: LICENSE
Requires-Dist: fastmcp>=2.0.0
Requires-Dist: heaven-framework>=0.1.0
Dynamic: author
Dynamic: classifier
Dynamic: keywords
Dynamic: license
Dynamic: license-file
Dynamic: requires-dist
Dynamic: requires-python
Dynamic: summary
